{
  "openapi": "3.0.0",
  "info": {
    "title": "API-Galapagos",
    "version": "1.0.0",
    "description": ""
  },
  "servers": [
    {
      "url": "{{url}}Usuario"
    },
    {
      "url": "{{url}}cliente"
    },
    {
      "url": "{{url}}cups"
    },
    {
      "url": "{{url}}Command"
    },
    {
      "url": "{{url}}ContratoPotencial"
    },
    {
      "url": "{{url}}PeriodoFactura"
    },
    {
      "url": "{{url}}Sips"
    },
    {
      "url": "{{url}}Contrato"
    },
    {
      "url": "{{url}}FacturaVentaCabecera"
    }
  ],
  "paths": {
    "/Token": {
      "parameters": [],
      "get": {
        "summary": "Token",
        "tags": [
          "Token"
        ],
        "parameters": [
          {
            "name": "User",
            "in": "header",
            "required": false,
            "example": "{{user-base64}}",
            "schema": {
              "type": "string"
            }
          },
          {
            "name": "Password",
            "in": "header",
            "required": false,
            "example": "{{password-base64}}",
            "schema": {
              "type": "string"
            }
          }
        ],
        "responses": {},
        "requestBody": {
          "content": {
            "application/json": {
              "schema": {
                "type": "object"
              },
              "example": {}
            }
          }
        }
      }
    },
    "/Token/Entorno/1": {
      "parameters": [],
      "get": {
        "summary": "Token con entorno",
        "tags": [
          "Token"
        ],
        "parameters": [
          {
            "name": "User",
            "in": "header",
            "required": false,
            "example": "{{user-base64}}",
            "schema": {
              "type": "string"
            }
          },
          {
            "name": "Password",
            "in": "header",
            "required": false,
            "example": "{{password-base64}}",
            "schema": {
              "type": "string"
            }
          }
        ],
        "responses": {},
        "requestBody": {
          "content": {
            "application/json": {
              "schema": {
                "type": "object"
              },
              "example": {}
            }
          }
        }
      }
    },
    "/InsertDatosClientes": {
      "parameters": [],
      "post": {
        "summary": "InsertDatosClientes",
        "tags": [
          "Cliente"
        ],
        "parameters": [
          {
            "name": "Enrypt-Response",
            "in": "header",
            "required": false,
            "example": "false",
            "schema": {
              "type": "boolean"
            }
          }
        ],
        "responses": {},
        "requestBody": {
          "content": {
            "application/json": {
              "schema": {
                "type": "object"
              },
              "example": null
            }
          }
        }
      }
    },
    "/GetClientePorDni/Empresa/1/Usuario/13/Dni/A86500774": {
      "parameters": [],
      "get": {
        "summary": "GetClientePorDni",
        "tags": [
          "Cliente"
        ],
        "parameters": [
          {
            "name": "IgnorarFormatoRespuesta",
            "in": "header",
            "required": false,
            "example": "{{ignorar-formato-respuesta}}",
            "schema": {
              "type": "string"
            }
          }
        ],
        "responses": {}
      }
    },
    "/ComprobarCupsActivo": {
      "parameters": [],
      "post": {
        "summary": "ComprobarCupsActivo",
        "tags": [
          "Cups"
        ],
        "parameters": [
          {
            "name": "IgnorarFormatoRespuesta",
            "in": "header",
            "required": false,
            "example": "{{ignorar-formato-respuesta}}",
            "schema": {
              "type": "string"
            }
          }
        ],
        "responses": {},
        "requestBody": {
          "content": {
            "application/json": {
              "schema": {
                "type": "string"
              },
              "example": "ES0031103034290004ML"
            }
          }
        }
      }
    },
    "/": {
      "parameters": [],
      "get": {
        "summary": "Cups",
        "tags": [
          "Cups"
        ],
        "parameters": [
          {
            "name": "IgnorarFormatoRespuesta",
            "in": "header",
            "required": false,
            "example": "{{ignorar-formato-respuesta}}",
            "schema": {
              "type": "string"
            }
          }
        ],
        "responses": {},
        "requestBody": {
          "content": {
            "application/json": {
              "schema": {
                "type": "object",
                "properties": {
                  "IdEmpresa": {
                    "type": "integer"
                  },
                  "IdUsuario": {
                    "type": "integer"
                  },
                  "MaxItems": {
                    "type": "integer"
                  }
                }
              },
              "example": {
                "IdEmpresa": 1,
                "IdUsuario": 13,
                "MaxItems": 12300
              }
            }
          }
        }
      },
      "post": {
        "summary": "ciudad.consultar",
        "tags": [
          "Command",
          "Callejero",
          "Ciudad"
        ],
        "parameters": [
          {
            "name": "CommandTraceMode",
            "in": "header",
            "required": false,
            "example": "{{command-trace-mode}}",
            "schema": {
              "type": "string"
            }
          }
        ],
        "responses": {},
        "requestBody": {
          "content": {
            "application/json": {
              "schema": {
                "type": "object"
              },
              "example": null
            }
          }
        }
      }
    },
    "/clonar": {
      "parameters": [],
      "post": {
        "summary": "Clonar",
        "tags": [
          "Command"
        ],
        "parameters": [
          {
            "name": "IgnorarFormatoRespuesta",
            "in": "header",
            "required": false,
            "example": "{{ignorar-formato-respuesta}}",
            "schema": {
              "type": "string"
            }
          }
        ],
        "responses": {},
        "requestBody": {
          "content": {
            "application/json": {
              "schema": {
                "type": "object"
              },
              "example": null
            }
          }
        }
      }
    },
    "/ProcesarCSV": {
      "parameters": [],
      "get": {
        "summary": "ProcesarCSV",
        "tags": [
          "Command"
        ],
        "parameters": [],
        "responses": {}
      }
    },
    "/ActualizarPasswordsClientes": {
      "parameters": [],
      "get": {
        "summary": "ActualizarPasswordsClientes",
        "tags": [
          "Command"
        ],
        "parameters": [],
        "responses": {}
      }
    },
    "/POST": {
      "parameters": [],
      "post": {
        "summary": "POST",
        "tags": [
          "ContratoPotencial"
        ],
        "parameters": [],
        "responses": {
          "default": {
            "headers": {},
            "description": "DEBUG"
          }
        },
        "requestBody": {
          "content": {
            "application/json": {
              "schema": {
                "type": "object",
                "properties": {
                  "ContratosPotenciales": {
                    "type": "array",
                    "items": {
                      "type": "object",
                      "properties": {
                        "Aclarador": {
                          "type": "string"
                        },
                        "AclaradorEnvio": {
                          "type": "string"
                        },
                        "ActivacionPrevista": {
                          "nullable": true
                        },
                        "Apellido1Titular": {
                          "type": "string"
                        },
                        "Bic": {
                          "type": "string"
                        },
                        "CalleEnvio": {
                          "type": "string"
                        },
                        "CallePuntoSuministro": {
                          "type": "string"
                        },
                        "CalleTitular": {
                          "type": "string"
                        },
                        "CiudadEnvio": {
                          "type": "string"
                        },
                        "CiudadSuministro": {
                          "type": "string"
                        },
                        "CiudadTitular": {
                          "type": "string"
                        },
                        "CodigoCNAE": {
                          "type": "string",
                          "format": "utc-millisec"
                        },
                        "CodigoCUPS": {
                          "type": "string"
                        },
                        "CodigoREEDistribuidora": {
                          "type": "string",
                          "format": "utc-millisec"
                        },
                        "CodPostal": {
                          "type": "string",
                          "format": "utc-millisec"
                        },
                        "Colectivo": {
                          "type": "string"
                        },
                        "CoreFechaFirma": {
                          "type": "string",
                          "format": "date-time"
                        },
                        "CPEnvio": {
                          "type": "string",
                          "format": "utc-millisec"
                        },
                        "CPTitular": {
                          "type": "string",
                          "format": "utc-millisec"
                        },
                        "EmailTitular": {
                          "type": "string",
                          "format": "email"
                        },
                        "FechaAlta": {
                          "nullable": true
                        },
                        "FechaContrato": {
                          "type": "string",
                          "format": "date-time"
                        },
                        "FechaEfecto": {
                          "nullable": true
                        },
                        "IBAN": {
                          "type": "string"
                        },
                        "IdContratoSituacion": {
                          "type": "integer"
                        },
                        "Identificador": {
                          "type": "string"
                        },
                        "IdentificadorPagador": {
                          "type": "string"
                        },
                        "IdModeloContrato": {
                          "type": "integer"
                        },
                        "IdSolicitudCambioTitular": {
                          "type": "string",
                          "format": "utc-millisec"
                        },
                        "IdUP": {
                          "type": "integer"
                        },
                        "NombreAgente": {
                          "type": "string"
                        },
                        "NombreEnvio": {
                          "type": "string"
                        },
                        "NombrePagador": {
                          "type": "string"
                        },
                        "NombreTitular": {
                          "type": "string"
                        },
                        "Numero": {
                          "type": "integer"
                        },
                        "NumeroEnvio": {
                          "type": "integer"
                        },
                        "NumeroTitular": {
                          "type": "integer"
                        },
                        "P1": {
                          "type": "number"
                        },
                        "P3": {
                          "type": "number"
                        },
                        "PerfilFacturacionContratoTarifa": {
                          "type": "string"
                        },
                        "PerfilFacturacionPeaje": {
                          "type": "string"
                        },
                        "ProvinciaEnvio": {
                          "type": "string"
                        },
                        "ProvinciaSuministro": {
                          "type": "string"
                        },
                        "ProvinciaTitular": {
                          "type": "string"
                        },
                        "RefCatastral": {
                          "nullable": true
                        },
                        "SolicitudTipoFechaEfecto": {
                          "type": "string"
                        },
                        "Tarifa": {
                          "type": "string"
                        },
                        "TarifaGrupo": {
                          "type": "string"
                        },
                        "TextoPeriodo": {
                          "type": "string"
                        },
                        "TextoTarifaAcceso": {
                          "type": "string"
                        },
                        "TextoTipoCobro": {
                          "type": "string"
                        },
                        "TextoTipoImpresion": {
                          "type": "string"
                        },
                        "TfnoTitular": {
                          "type": "string",
                          "format": "utc-millisec"
                        },
                        "TipoSolicitud": {
                          "type": "string"
                        }
                      }
                    }
                  },
                  "IdEmpresa": {
                    "type": "integer"
                  },
                  "IdUsuario": {
                    "type": "integer"
                  }
                }
              },
              "example": {
                "ContratosPotenciales": [
                  {
                    "Aclarador": "Bq Es Pl Pu ",
                    "AclaradorEnvio": "Bq Es Pl Pu ",
                    "ActivacionPrevista": null,
                    "Apellido1Titular": "Prieto Garlito",
                    "Bic": "BBVAESMMXXX",
                    "CalleEnvio": "Avenida Alcalde Narciso Martín Navarro",
                    "CallePuntoSuministro": "Avenida Alcalde Narciso Martín Navarro",
                    "CalleTitular": "Avenida Alcalde Narciso Martín Navarro",
                    "CiudadEnvio": "AYAMONTE",
                    "CiudadSuministro": "AYAMONTE",
                    "CiudadTitular": "AYAMONTE",
                    "CodigoCNAE": "9820",
                    "CodigoCUPS": "ES0031102145357003JK",
                    "CodigoREEDistribuidora": "23",
                    "CodPostal": "21400",
                    "Colectivo": "PERSONAS FISICAS",
                    "CoreFechaFirma": "2025-02-18T15:58:49Z",
                    "CPEnvio": "21400",
                    "CPTitular": "21400",
                    "EmailTitular": "juanjoseprietogarlito@gmail.com",
                    "FechaAlta": null,
                    "FechaContrato": "2025-02-18T15:58:49Z",
                    "FechaEfecto": null,
                    "IBAN": "ES6501820454850201615554",
                    "IdContratoSituacion": 4,
                    "Identificador": "29493412Y",
                    "IdentificadorPagador": "29493412Y",
                    "IdModeloContrato": 4,
                    "IdSolicitudCambioTitular": "1",
                    "IdUP": 3,
                    "NombreAgente": "integracion_api",
                    "NombreEnvio": "Juan Jose Prieto Garlito",
                    "NombrePagador": "Juan Jose Prieto Garlito",
                    "NombreTitular": "Juan Jose",
                    "Numero": 8,
                    "NumeroEnvio": 8,
                    "NumeroTitular": 8,
                    "P1": 2.2,
                    "P3": 2.2,
                    "PerfilFacturacionContratoTarifa": "ML Factura BT <=10 Kw",
                    "PerfilFacturacionPeaje": "ML Factura BT <=15 Kw",
                    "ProvinciaEnvio": "HUELVA",
                    "ProvinciaSuministro": "HUELVA",
                    "ProvinciaTitular": "HUELVA",
                    "RefCatastral": null,
                    "SolicitudTipoFechaEfecto": "A",
                    "Tarifa": "2.0TD ML",
                    "TarifaGrupo": "Tarifa 24h (V1)",
                    "TextoPeriodo": "MENSUAL",
                    "TextoTarifaAcceso": "2.0TD",
                    "TextoTipoCobro": "DOMICILIADO",
                    "TextoTipoImpresion": "E",
                    "TfnoTitular": "+34642784016",
                    "TipoSolicitud": "MZ"
                  }
                ],
                "IdEmpresa": 1,
                "IdUsuario": 13
              }
            }
          }
        }
      }
    },
    "/GetDTOAllPeriodos/Empresa/1/Usuario/13/Linea/1": {
      "parameters": [],
      "get": {
        "summary": "Obtener Perfiles Facturacion",
        "tags": [
          "ContratoPotencial"
        ],
        "parameters": [
          {
            "name": "IgnorarFormatoRespuesta",
            "in": "header",
            "required": false,
            "example": "true",
            "schema": {
              "type": "boolean"
            }
          }
        ],
        "responses": {}
      }
    },
    "/ELE/GetClientesPost": {
      "parameters": [],
      "post": {
        "summary": "Electricidad",
        "tags": [
          "Sips"
        ],
        "parameters": [],
        "responses": {},
        "requestBody": {
          "content": {
            "application/json": {
              "schema": {
                "type": "object",
                "properties": {
                  "CodigoCUPS": {
                    "type": "string"
                  },
                  "NombreEmpresaDistribuidora": {
                    "type": "string"
                  },
                  "MunicipioPS": {
                    "type": "string"
                  },
                  "CodigoProvinciaPS": {
                    "type": "string"
                  },
                  "CodigoPostalPS": {
                    "type": "string"
                  },
                  "CodigoTarifaATREnVigor": {
                    "type": "string"
                  },
                  "ListCUPS": {
                    "type": "string"
                  },
                  "LoadAllDatosCliente": {
                    "type": "boolean"
                  },
                  "LoadConsumos": {
                    "type": "boolean"
                  },
                  "IsExist": {
                    "type": "boolean"
                  }
                }
              },
              "example": {
                "CodigoCUPS": "ES0021000000750542CA",
                "NombreEmpresaDistribuidora": "",
                "MunicipioPS": "",
                "CodigoProvinciaPS": "",
                "CodigoPostalPS": "",
                "CodigoTarifaATREnVigor": "",
                "ListCUPS": "",
                "LoadAllDatosCliente": true,
                "LoadConsumos": true,
                "IsExist": false
              }
            }
          }
        }
      }
    },
    "/GAS/GetClientesPost": {
      "parameters": [],
      "post": {
        "summary": "Gas",
        "tags": [
          "Sips"
        ],
        "parameters": [],
        "responses": {},
        "requestBody": {
          "content": {
            "application/json": {
              "schema": {
                "type": "object",
                "properties": {
                  "CodigoCUPS": {
                    "type": "string"
                  },
                  "NombreEmpresaDistribuidora": {
                    "type": "string"
                  },
                  "MunicipioPS": {
                    "type": "string"
                  },
                  "CodigoProvinciaPS": {
                    "type": "string"
                  },
                  "CodigoPostalPS": {
                    "type": "string"
                  },
                  "CodigoTarifaATREnVigor": {
                    "type": "string"
                  },
                  "ListCUPS": {
                    "type": "array",
                    "items": {}
                  },
                  "LoadAllDatosCliente": {
                    "type": "boolean"
                  },
                  "LoadConsumos": {
                    "type": "boolean"
                  },
                  "IsExist": {
                    "type": "boolean"
                  }
                }
              },
              "example": {
                "CodigoCUPS": "ES0217020207750908QM",
                "NombreEmpresaDistribuidora": "",
                "MunicipioPS": "",
                "CodigoProvinciaPS": "",
                "CodigoPostalPS": "",
                "CodigoTarifaATREnVigor": "",
                "ListCUPS": [],
                "LoadAllDatosCliente": true,
                "LoadConsumos": true,
                "IsExist": false
              }
            }
          }
        }
      }
    },
    "/GetIdContratoPDFPorFechaAlta/Empresa/1/Usuario/13/Contrato/10913": {
      "parameters": [],
      "get": {
        "summary": "GetIdContratoPDFPorFechaAlta",
        "tags": [
          "Contrato"
        ],
        "parameters": [],
        "responses": {}
      }
    },
    "/GetDTOAllContratos": {
      "parameters": [],
      "post": {
        "summary": "GetDTOAllContratos",
        "tags": [
          "Contrato"
        ],
        "parameters": [
          {
            "name": "IgnorarFormatoRespuesta",
            "in": "header",
            "required": false,
            "example": "{{ignorar-formato-respuesta}}",
            "schema": {
              "type": "string"
            }
          }
        ],
        "responses": {},
        "requestBody": {
          "content": {
            "application/json": {
              "schema": {
                "type": "object"
              },
              "example": null
            }
          }
        }
      }
    },
    "/GetByIds": {
      "parameters": [],
      "post": {
        "summary": "GetByIds",
        "tags": [
          "FacturaVentaCabecera"
        ],
        "parameters": [
          {
            "name": "IgnorarFormatoRespuesta",
            "in": "header",
            "required": false,
            "example": "{{ignorar-formato-respuesta}}",
            "schema": {
              "type": "string"
            }
          }
        ],
        "responses": {},
        "requestBody": {
          "content": {
            "application/json": {
              "schema": {
                "type": "object",
                "properties": {
                  "IdEmpresa": {
                    "type": "integer"
                  },
                  "IdUsuario": {
                    "type": "integer"
                  },
                  "Ids": {
                    "type": "array",
                    "items": {
                      "type": "integer"
                    }
                  }
                }
              },
              "example": {
                "IdEmpresa": 2,
                "IdUsuario": 1,
                "Ids": [
                  32,
                  30,
                  28,
                  27
                ]
              }
            }
          }
        }
      }
    },
    "/Empresa/1/Usuario/13/IdFacturaVentaCabecera/17408": {
      "parameters": [],
      "get": {
        "summary": "FacturaVentaCabecera Empresa/1/Usuario/13/IdFacturaVentaCabecera/17408",
        "tags": [
          "FacturaVentaCabecera"
        ],
        "parameters": [
          {
            "name": "IgnorarFormatoRespuesta",
            "in": "header",
            "required": false,
            "example": "{{ignorar-formato-respuesta}}",
            "schema": {
              "type": "string"
            }
          }
        ],
        "responses": {},
        "requestBody": {
          "content": {
            "application/json": {
              "schema": {
                "type": "object",
                "properties": {
                  "IdEmpresa": {
                    "type": "integer"
                  },
                  "IdUsuario": {
                    "type": "integer"
                  },
                  "FechaDesde": {
                    "type": "string",
                    "format": "date"
                  },
                  "FechaHasta": {
                    "type": "string",
                    "format": "date"
                  },
                  "DevolverPotenciaContratada": {
                    "type": "boolean"
                  },
                  "DevolverConsumo": {
                    "type": "boolean"
                  }
                }
              },
              "example": {
                "IdEmpresa": 1,
                "IdUsuario": 1,
                "FechaDesde": "2025-01-01",
                "FechaHasta": "2025-01-28",
                "DevolverPotenciaContratada": true,
                "DevolverConsumo": true
              }
            }
          }
        }
      }
    }
  }
}